odoo/addons/pos_container/README.rst
odoo/addons/pos_container/__init__.py
odoo/addons/pos_container/__manifest__.py
odoo/addons/pos_container/data/product.xml
odoo/addons/pos_container/demo/demo.xml
odoo/addons/pos_container/i18n/fr.po
odoo/addons/pos_container/i18n/pos_container.pot
odoo/addons/pos_container/models/__init__.py
odoo/addons/pos_container/models/barcode.py
odoo/addons/pos_container/models/container.py
odoo/addons/pos_container/models/pos_order_line.py
odoo/addons/pos_container/readme/CONTRIBUTORS.rst
odoo/addons/pos_container/readme/DESCRIPTION.rst
odoo/addons/pos_container/readme/USAGE.rst
odoo/addons/pos_container/security/ir.model.access.csv
odoo/addons/pos_container/static/description/index.html
odoo/addons/pos_container/static/src/css/container.css
odoo/addons/pos_container/static/src/js/container.js
odoo/addons/pos_container/static/src/js/models_and_db.js
odoo/addons/pos_container/static/src/js/tests.js
odoo/addons/pos_container/static/src/xml/pos.xml
odoo/addons/pos_container/templates/templates.xml
odoo/addons/pos_container/tests/__init__.py
odoo/addons/pos_container/tests/test_pos_container.py
odoo/addons/pos_container/views/container.xml
odoo12_addon_pos_container-12.0.1.0.0.99.dev85.dist-info/METADATA
odoo12_addon_pos_container-12.0.1.0.0.99.dev85.dist-info/WHEEL
odoo12_addon_pos_container-12.0.1.0.0.99.dev85.dist-info/top_level.txt
odoo12_addon_pos_container-12.0.1.0.0.99.dev85.dist-info/RECORD
