Metadata-Version: 2.1
Name: odoo12-addon-pos-container
Version: 12.0.1.0.0.99.dev85
Summary: Allows managing pre-weighted containers for bulk shop
Home-page: https://github.com/OCA/pos/
Author: Coop IT Easy SCRLfs, Odoo Community Association (OCA)
Author-email: support@odoo-community.org
License: AGPL-3
Platform: UNKNOWN
Classifier: Programming Language :: Python
Classifier: Framework :: Odoo
Classifier: License :: OSI Approved :: GNU Affero General Public License v3
Requires-Python: >=3.5
Requires-Dist: odoo (<12.1dev,>=12.0a)
